Metadata-Version: 2.1
Name: BRUH_Iakushin
Version: 0.0.1
Summary: bruuuuuh
Author: Nikita
Author-email: nikitaakusin222@gmail.com
